recognizesize/ImageManager.py
recognizesize/PersonRecognizer.py
recognizesize/SizeRecognizer.py
recognizesize/__init__.py
recognizesize/recognizesize.py
recognizesize-2.2.dist-info/LICENSE
recognizesize-2.2.dist-info/METADATA
recognizesize-2.2.dist-info/WHEEL
recognizesize-2.2.dist-info/top_level.txt
recognizesize-2.2.dist-info/RECORD
