Metadata-Version: 2.1
Name: recognizesize
Version: 2.2
Summary: A package to recognize size of your body in format XS/S/M/L/XL
Home-page: https://github.com/Reflect-Me/recognize-size
Author: Maxim Laptev
Author-email: maks-laptev.03@mail.ru
License: UNKNOWN
Platform: UNKNOWN
Classifier: Programming Language :: Python :: 3.9
Classifier: License :: OSI Approved :: GNU General Public License v3 (GPLv3)
Requires-Dist: matplotlib
Requires-Dist: numpy
Requires-Dist: opencv-contrib-python
Requires-Dist: Pillow
Requires-Dist: torch
Requires-Dist: torchvision
